astra/__init__.py
astra/core/__init__.py
astra/core/annotations.py
astra_core-0.1.0.dist-info/METADATA
astra_core-0.1.0.dist-info/WHEEL
astra_core-0.1.0.dist-info/top_level.txt
astra_core-0.1.0.dist-info/zip-safe
astra_core-0.1.0.dist-info/RECORD
